aiforge/__init__.py
forgeai-0.0.0.dist-info/METADATA
forgeai-0.0.0.dist-info/WHEEL
forgeai-0.0.0.dist-info/top_level.txt
forgeai-0.0.0.dist-info/RECORD
